video_processing_framework/__init__.py
video_processing_framework/skeleton.py
video_processing_framework-0.1.0.dist-info/LICENSE.txt
video_processing_framework-0.1.0.dist-info/METADATA
video_processing_framework-0.1.0.dist-info/WHEEL
video_processing_framework-0.1.0.dist-info/top_level.txt
video_processing_framework-0.1.0.dist-info/RECORD
